llama_index/llms/novita/__init__.py
llama_index/llms/novita/base.py
llama_index_llms_novita-0.2.1.dist-info/METADATA
llama_index_llms_novita-0.2.1.dist-info/WHEEL
llama_index_llms_novita-0.2.1.dist-info/licenses/LICENSE
llama_index_llms_novita-0.2.1.dist-info/RECORD
