Metadata-Version: 2.4
Name: llama-index-llms-novita
Version: 0.2.1
Summary: llama-index llms novita integration
Author-email: Your Name <you@example.com>
License-Expression: MIT
License-File: LICENSE
Requires-Python: <4.0,>=3.9
Requires-Dist: llama-index-core<0.15,>=0.13.0
Requires-Dist: llama-index-llms-openai-like>=0.3.4
Requires-Dist: openai>=1.0.0
